wakka/__init__.py
wakka/wakka.py
wakka-1.0.dist-info/LICENSE
wakka-1.0.dist-info/METADATA
wakka-1.0.dist-info/WHEEL
wakka-1.0.dist-info/top_level.txt
wakka-1.0.dist-info/RECORD
