Metadata-Version: 2.1
Name: wakka
Version: 1.0
Summary: A wakka package.
Author-email: Tomoya Ogawa <t.ogawa@ogatomo.net>
Classifier: Programming Language :: Python :: 3
Classifier: License :: OSI Approved :: MIT License
Classifier: Operating System :: OS Independent
Requires-Python: >=3.1
License-File: LICENSE
